synapsebev/__init__.py
synapsebev/src/__init__.py
synapsebev/src/synapse_eyes/__init__.py
synapsebev/src/synapse_eyes/color_codes.py
synapsebev/src/synapse_eyes/generate_cost_map.py
synapsebev/src/synapse_eyes/metrics_calculator.py
synapsebev/src/synapse_eyes/robot_simulator.py
synapsebev/src/synapse_eyes/warehouse_manager.py
synapsebev/src/synapse_eyes/warehouse_occ_grid_db.py
synapsebev/src/synapse_plan/__init__.py
synapsebev/src/synapse_plan/a_star.py
synapsebev/src/synapse_plan/create_plan.py
synapsebev/src/synapse_plan/environment.py
synapsebev/src/synapse_plan/utils.py
synapsebev/src/synapse_plan/visualize.py
synapsebev/src/synapse_plan/configs/__init__.py
synapsebev-0.0.4.dist-info/LICENSE
synapsebev-0.0.4.dist-info/METADATA
synapsebev-0.0.4.dist-info/WHEEL
synapsebev-0.0.4.dist-info/top_level.txt
synapsebev-0.0.4.dist-info/RECORD
